Metadata-Version: 1.0
Name: dateconfig
Version: 1.2
Summary: Format date
Home-page: UNKNOWN
Author: Python Wiz
Author-email: pydatepackage@gmail.com
License: UNKNOWN
Platform: UNKNOWN
